autogame/__init__.py
autogame-0.0.dist-info/LICENSE
autogame-0.0.dist-info/METADATA
autogame-0.0.dist-info/WHEEL
autogame-0.0.dist-info/top_level.txt
autogame-0.0.dist-info/RECORD
