Metadata-Version: 2.1
Name: autogame
Version: 0.0
Summary: A python framework for automatic game playing, which can be used to develop automatic game scripts.
Home-page: https://github.com/invokerrrr/autogame-python
Author: Invoker
Author-email: invoker-bot@outlook.com
License: MIT
Download-URL: https://github.com/invokerrrr/autogame-python/archive/main.zip
Keywords: automatic game python development script
Platform: UNKNOWN
Classifier: Development Status :: 1 - Planning
Classifier: Environment :: Console
Classifier: Environment :: GPU
Classifier: Intended Audience :: Developers
Classifier: License :: OSI Approved :: MIT License
Classifier: Natural Language :: English
Classifier: Programming Language :: Python
Classifier: Topic :: Games/Entertainment :: Simulation
Classifier: Topic :: Software Development :: Libraries :: Python Modules
Classifier: Operating System :: OS Independent
License-File: LICENSE
Requires-Dist: opencv-python
Requires-Dist: tensorflow
Provides-Extra: gpu
Requires-Dist: tensorflow-gpu ; extra == 'gpu'
